<?xml version="1.0" encoding="UTF-8"?>
<cause>
  <description>Habitat for Humanity International is a nonprofit, ecumenical Christian housing ministry. HFHI seeks to eliminate poverty housing and homelessness from the world, and to make decent shelter a matter of conscience and action.

1. Work in partnership with God and people everywhere

2. Develop simple affordable housing for people in need

3. Empower people to grow into all that God intended</description>
  <mission>provide funding for an organization that makes the dream of a home a reality.</mission>
  <name>Maumee Valley Habitat for Humanity</name>
  <canonical-url>http://www.causes.com/causes/762</canonical-url>
  <member-count type="integer">7</member-count>
  <total-raised type="decimal">0.0</total-raised>
  <photo-url>https://causes-prod.s3.amazonaws.com/photos/25B/IELS.jpg</photo-url>
</cause>
