<?xml version="1.0" encoding="UTF-8"?>
<cause>
  <description>we are a small group that is tired of desicions being made based purely on their agendas and what their party wants. the point of the government is to provide what is best for the people, not their own wallets

1. Right/Wrong should be the only bias

2. votes and descisions should not be for monetary gains

3. bicameral legilature is only a name, not a standard</description>
  <mission>convice politicians that biased decisions are wrong decisions</mission>
  <name>politics shouldnt be about biases</name>
  <canonical-url>http://www.causes.com/causes/1753</canonical-url>
  <member-count type="integer">7</member-count>
  <total-raised type="decimal">0.0</total-raised>
  <photo-url>https://causes-prod.s3.amazonaws.com/photos/R8/To/Hq/2x/DQ/nH/hm6S.jpg</photo-url>
</cause>
