<?xml version="1.0" encoding="UTF-8"?>
<cause>
  <description>It's time the Shi'a youth in the world unite as one.

1. Spread Shi'a unity

2. Share Knowledge and resources

3. Prepare for the coming of our Imam (atfs)</description>
  <mission>Unite the Shia youth worldwide</mission>
  <name>Shia Youth Unity</name>
  <canonical-url>http://www.causes.com/causes/1805</canonical-url>
  <member-count type="integer">2781</member-count>
  <total-raised type="decimal">25.18</total-raised>
  <photo-url>https://causes-prod.s3.amazonaws.com/photos/Lf/fF/dg/oA/Zf/hN/7e/nzS.jpg</photo-url>
</cause>
