<?xml version="1.0" encoding="UTF-8"?>
<cause>
  <description>Sigma Alpha Iota Philanthropies, Inc., created in 1974 as a tax-exempt, nonprofit organization, is the charitable arm of Sigma Alpha Iota, international music fraternity.

http://www.sai-national.org/phil/

A gift to SAI Philanthropies is "A Gift to Music". Your continued interest and financial support are greatly appreciated. All gifts are tax deductible. Please make checks payable to SAI Philanthropies, Inc. and mail to:
SAI Philanthropies, Inc.
One Tunnel Road
Asheville, NC 28805 


1. Promote all phases of music, including history, composition, performance, appreciation, and criticism, and to aid and recognize those learning or serving in any field of music. 

2. Raise the standards of all aspects of music among students and teachers in American colleges, conservatories, and universities. 

3. Develop stronger bonds of musical interest and understanding between foreign countries and the United States of America. 

4. Receive property of any kind, whether real or personal, and to administer and apply such property and the income there from exclusively for charitable, educational, and literary purposes. </description>
  <mission>To promote all aspects of music creation, performance and scholarship; and encourage service for and through music on the campus, in the community, in the nation, and throughout the world.</mission>
  <name>Sigma Alpha Iota Philanthropies, Inc.</name>
  <canonical-url>http://www.causes.com/causes/2499</canonical-url>
  <member-count type="integer">2533</member-count>
  <total-raised type="decimal">248.99</total-raised>
  <photo-url>https://causes-prod.s3.amazonaws.com/photos/TL/8e/7V/1R/DJ/LX/FwTS.jpg</photo-url>
</cause>
