<?xml version="1.0" encoding="UTF-8"?>
<cause>
  <description>This club is for all those cool kids out there that are sick and tired of people beating the shit out of cute little seals!! I know I am!!

1. their awesome

2. their cute

3. their white</description>
  <mission>stop human beings from going out and clubing seals to death for there fur!!</mission>
  <name>STOP THE CLUBING OF BABY SEALS!!</name>
  <canonical-url>http://www.causes.com/causes/3664</canonical-url>
  <member-count type="integer">450</member-count>
  <total-raised type="decimal">0.0</total-raised>
  <photo-url>https://causes-prod.s3.amazonaws.com/photos/CM/Ew/Vf/Ne/Wb/bz/nrjS.jpg</photo-url>
</cause>
