<?xml version="1.0" encoding="UTF-8"?>
<cause>
  <description>P.T. Anderson is the acclaimed director of such films as: Magnolia, Boogie Nights, and Punch Drunk Love. His films have a unique quality and tone, and they are have the right to be appreciated on so many higher levels. Please join...

1. Watch His Films

2. Analyze Plot Development and Camera Angles

3. Praise His Films

4. Be Happy.</description>
  <mission>Praise His Films</mission>
  <name>P.T. Anderson is Filmmaking God, too</name>
  <canonical-url>http://www.causes.com/causes/4430</canonical-url>
  <member-count type="integer">3</member-count>
  <total-raised type="decimal">0.0</total-raised>
  <photo-url>https://causes-prod.s3.amazonaws.com/photos/uJ/R6/Ed/IB/eS/4E/espS.jpg</photo-url>
</cause>
