<?xml version="1.0" encoding="UTF-8"?>
<cause>
  <description>Elderly sex workers live in appalling conditions on the streets of Mexico City. Independent sex workers have the need to come together to hold seminars, organize reflection groups, and take primary- to high school-classes. 


Casa Xochiquetzal, a community center in one of the poorest and most marginalized neighborhoods in Mexico City, will give older and independent sex workers the space and opportunity to gain dignity and learn about their human rights.




1. Sex workers require space and opportunity to learn about their rights and empower themselves</description>
  <mission>to give sex workers in Mexico a place to empower themselves through alternate forms of income-generating activities and education.</mission>
  <name>Empower Sex Workers</name>
  <canonical-url>http://www.causes.com/causes/5278</canonical-url>
  <member-count type="integer">380</member-count>
  <total-raised type="decimal">0.0</total-raised>
  <photo-url>https://causes-prod.s3.amazonaws.com/photos/b8/RY/6P/aw/Mw/hx/Wf2S.jpg</photo-url>
</cause>
