<?xml version="1.0" encoding="UTF-8"?>
<cause>
  <description>Rachel was 21 years old when she passed away while waiting on a kidney and a liver. When she was 3 and a half years old she was diagnoised with a very rare cancer that affects the liver. In her lifetime she had one liver transplant ans 3 kidney transplant. She also endured many blood tranfusions. 

1. Awareness needs to be raised

2. Recycle yourself and help save a life</description>
  <mission>Raise transplant awareness</mission>
  <name>The Rachel Heaton Fund</name>
  <canonical-url>http://www.causes.com/causes/5418</canonical-url>
  <member-count type="integer">16</member-count>
  <total-raised type="decimal">0.0</total-raised>
  <photo-url>https://causes-prod.s3.amazonaws.com/photos/EV/vs/OT/nB/Zp/ag/fT6S.jpg</photo-url>
</cause>
