<?xml version="1.0" encoding="UTF-8"?>
<cause>
  <description>Pescetarians eat no meat (chicken, pork, ham, etc.). So, why not just be a vegetarian? Aren't they the same thing? Nope. Pescetarians don't eat land animals. But they do eat fish and other seafoods. Yay!

1. Animals need to be saved, but sushi is too good to give up.</description>
  <mission>Save all animals (except fish...sushi is too good)!</mission>
  <name>Pescetarianism</name>
  <canonical-url>http://www.causes.com/causes/5667</canonical-url>
  <member-count type="integer">18</member-count>
  <total-raised type="decimal">0.0</total-raised>
  <photo-url>https://causes-prod.s3.amazonaws.com/photos/1p/ls/CE/e5/Xl/FO/TNcS.jpg</photo-url>
</cause>
