<?xml version="1.0" encoding="UTF-8"?>
<cause>
  <description>MasterOf Disaster is a smart, sexy, and young guys that needs to be steered down the right path!!!
He needs support and YOU can help, we have to make sure those bad influences in his life don't get to him!!!!

1. MasterOf Disaster has to become successful in his life.

2. Master0f Disaster is the future</description>
  <mission>Make sure his life goes down the right path</mission>
  <name>Save MasterOf Disaster from DISASTER!!!!</name>
  <canonical-url>http://www.causes.com/causes/6371</canonical-url>
  <member-count type="integer">1</member-count>
  <total-raised type="decimal">0.0</total-raised>
  <photo-url>https://causes-prod.s3.amazonaws.com/photos/IV/wG/yn/mN/E2/Hh/HZ7S.jpg</photo-url>
</cause>
