<?xml version="1.0" encoding="UTF-8"?>
<cause>
  <description>you might not know it but more than 100 animals over NA are being abused tested on harmed in general. these animals are dying and asking for your help- be genorous and save them!

1. animals have rights

2. animals feel pain like humans</description>
  <mission>raise as much money to save animals all over north america from abuse testing and fighting etc.</mission>
  <name>Animal Abuse, fighting, abandoning and testing- STOP ALL OF IT NOW!</name>
  <canonical-url>http://www.causes.com/causes/6440</canonical-url>
  <member-count type="integer">15185</member-count>
  <total-raised type="decimal">524.69</total-raised>
  <photo-url>https://causes-prod.s3.amazonaws.com/photos/8j/va/Kf/eG/CP/aL/rZFS.jpg</photo-url>
</cause>
