<?xml version="1.0" encoding="UTF-8"?>
<cause>
  <description>To start a campaign of terrorism against terrorists making the world safer for everyone...



Except terrorists.






1. Terrorism isnt a bad thing when its against terrorists!

2. Fight fire with fun!</description>
  <mission>Bring terrorism to the terrorists</mission>
  <name>US Terrorists against Terrorism</name>
  <canonical-url>http://www.causes.com/causes/6665</canonical-url>
  <member-count type="integer">15</member-count>
  <total-raised type="decimal">0.0</total-raised>
  <photo-url>https://causes-prod.s3.amazonaws.com/photos/UE/1C/dH/1u/jy/x2/3JYS.jpg</photo-url>
</cause>
