<?xml version="1.0" encoding="UTF-8"?>
<cause>
  <description>Vi startar h&#228;r, vi startar nu en gemensam kamp f&#246;r ett b&#228;ttre samh&#228;lle och regeringsskifte 2010.

Finns som grupp ocks&#229;!
http://www.facebook.com/group.php?gid=3249778969

Om ni ger pengar h&#228;r s&#229; g&#229;r det till Sv.Transportarbetaref&#246;rbundets motsvarighet i USA, Teamsters (eftersom man bara kunde v&#228;lja bland ett antal fastst&#228;llda organisationer att donera till). 

10 000 Medlemmar den 14/11 2007
10 500 Medlemmar den 26/11 2007

1. F&#246;rena oss

2. Organisera oss

3. Ta ledningen och makten</description>
  <mission>Samh&#228;llsomst&#246;rtning 2010</mission>
  <name>Byt regering - Byt politik 2010</name>
  <canonical-url>http://www.causes.com/causes/7266</canonical-url>
  <member-count type="integer">15732</member-count>
  <total-raised type="decimal">0.0</total-raised>
  <photo-url>https://causes-prod.s3.amazonaws.com/photos/Lh/o3/nz/I3/XK/pF/QPxS.jpg</photo-url>
</cause>
