<?xml version="1.0" encoding="UTF-8"?>
<cause>
  <description>A middle-man foundation brought to you by Andrew Biscay that directly forwards one hundred percent of all funds raised to making the world a better place. This month's featured beneficiary is the American Cancer Society Eastern Division, but more specifically: Relay for Life. 


1. Help raise awareness! </description>
  <mission>Fight Global Stuff </mission>
  <name>The Andrew Biscay Foundation</name>
  <canonical-url>http://www.causes.com/causes/7910</canonical-url>
  <member-count type="integer">3</member-count>
  <total-raised type="decimal">0.0</total-raised>
  <photo-url>https://causes-prod.s3.amazonaws.com/photos/sr/3v/pg/kT/Wq/Fw/h6OS.jpg</photo-url>
</cause>
