<?xml version="1.0" encoding="UTF-8"?>
<cause>
  <description>Kabbalah - a 4000 year old body of spiritual wisdom - holds all the secrets of the universe and acts as a map through the mysteries of the human mind, body and soul.

Kabbalah is here to be used by all humanity to unify the world.

The Kabbalah Centre has a single mission which is to create simple happiness, permanent peace and lasting fulfillment for every person by continuing the Kabbalistic lineage and making the ancient wisdom accessible and available for the purpose of ending pain and suffering.

1. There are universal spiritual laws that effect everyone single one of us regardless of faith, race or any other defining factors.  Understanding these laws helps to unify all people</description>
  <mission>Create simple happiness, permanent peace and lasting fulfillment for every person</mission>
  <name>The Kabbalah Centre</name>
  <canonical-url>http://www.causes.com/causes/8311</canonical-url>
  <member-count type="integer">1198</member-count>
  <total-raised type="decimal">689.0</total-raised>
  <photo-url>https://causes-prod.s3.amazonaws.com/photos/Qe/jk/xb/ct/a2/5Y/XbxS.jpg</photo-url>
</cause>
