<?xml version="1.0" encoding="UTF-8"?>
<cause>
  <description>we are starting a nation wide program to save the real oompa loompas that are struggling in the harsh conditions of the great ruler luffanduh stoyanovitch in buffarieauh.

1. to save the oompa loompas

2. to make buffarieauh a better place

3. to over rule luffanduh stoyanovitch</description>
  <mission>save the oompa loompas that live in buffarieauh</mission>
  <name>save the real oompa loompas in buffarieauh</name>
  <canonical-url>http://www.causes.com/causes/8375</canonical-url>
  <member-count type="integer">36</member-count>
  <total-raised type="decimal">0.0</total-raised>
  <photo-url>https://causes-prod.s3.amazonaws.com/photos/Hk/NA/yT/DH/tV/UF/CKJS.jpg</photo-url>
</cause>
