<?xml version="1.0" encoding="UTF-8"?>
<cause>
  <description>Dedicated to creating tools and services to make charitable giving part of our everyday lives, JustGive is a nonprofit organization whose mission is to increase charitable giving by connecting people with the charities and causes they care most about.

1. Our goal is to connect you with the charities that you care about in the most convenient, secure manner possible. </description>
  <mission>increase charitable giving by connecting people with the charities and causes they care most about.</mission>
  <name>Make a Difference</name>
  <canonical-url>http://www.causes.com/causes/8537</canonical-url>
  <member-count type="integer">12</member-count>
  <total-raised type="decimal">85.0</total-raised>
  <photo-url>https://causes-prod.s3.amazonaws.com/photos/iX/hv/Fa/cp/Xm/n8/p8cS.jpg</photo-url>
</cause>
