<?xml version="1.0" encoding="UTF-8"?>
<cause>
  <description>Our goal is to reach out to more potential voters in the 2008 presidential election. We believe Barack Obama is a leader with almost a  Kennedy-esque mystique and rhetoric who is clearly the most apt presidential candidate.

1. Barack Obama is the best candidate in the 2008 election

2. Obama is the rare breed of politician that has both electability and integrity 

3. All the other candidates suck</description>
  <mission>Help Elect Barack Obama</mission>
  <name>Obama 08</name>
  <canonical-url>http://www.causes.com/causes/8729</canonical-url>
  <member-count type="integer">9</member-count>
  <total-raised type="decimal">0.0</total-raised>
  <photo-url>https://causes-prod.s3.amazonaws.com/photos/6j/ry/SX/xE/zr/Rr/HBES.jpg</photo-url>
</cause>
