<?xml version="1.0" encoding="UTF-8"?>
<cause>
  <description>Help me raise money for the IWK Hospital.  The hospital needs the money to buy more equipment and beds. 

1. Health care is a universal right.</description>
  <mission>raise money for the hospital</mission>
  <name>IWK Health Foundation</name>
  <canonical-url>http://www.causes.com/causes/9335</canonical-url>
  <member-count type="integer">2756</member-count>
  <total-raised type="decimal">12.0</total-raised>
  <photo-url>https://causes-prod.s3.amazonaws.com/photos/yg/ys/Fn/V3/oK/7U/yKgS.jpg</photo-url>
</cause>
